{
  "updated": "2026-06-15T07:39:00+09:00",
  "todays_call": "原油価格の急落が素材セクターを直撃、WTI▲4.24%、ブレント▲3.62%と大幅安となり、INPEX（1605）には年間約▲200億円の下押し圧力（ブレント$84.17は会社前提$63比+$21だが前日比では大幅下落）。一方で非鉄は明暗分かれ、LME銅+1.27%上昇で住友鉱山（5713）に+約8億円のプラス、金も+2.22%と堅調で副産物利益として+約95億円の押し上げ要因となる。原油急落の背景には地政学リスク後退や需要懸念があるとみられ、エネルギー関連（INPEX、ENEOS）には当面逆風が続く可能性がある一方、銅の上昇トレンド継続は製造業回復期待を示唆している。",
  "data_used": {
    "commodities": [
      "copper",
      "gold",
      "wti",
      "brent",
      "usdjpy"
    ],
    "high_alerts": 2,
    "medium_alerts": 2
  }
}